LICENSE
MANIFEST.in
README.md
setup.cfg
setup.py
django_dragndrop_related.egg-info/PKG-INFO
django_dragndrop_related.egg-info/SOURCES.txt
django_dragndrop_related.egg-info/dependency_links.txt
django_dragndrop_related.egg-info/not-zip-safe
django_dragndrop_related.egg-info/requires.txt
django_dragndrop_related.egg-info/top_level.txt
dragndrop_related/__init__.py
dragndrop_related/views.py
dragndrop_related/templates/admin/dragndrop_related/change_form.html
example_project/__init__.py
example_project/asgi.py
example_project/manage.py
example_project/settings.py
example_project/urls.py
example_project/wsgi.py
example_project/gallery/__init__.py
example_project/gallery/admin.py
example_project/gallery/apps.py
example_project/gallery/models.py
example_project/gallery/migrations/0001_initial.py
example_project/gallery/migrations/__init__.py
example_project/library/__init__.py
example_project/library/admin.py
example_project/library/apps.py
example_project/library/models.py
example_project/library/migrations/0001_initial.py
example_project/library/migrations/__init__.py