Metadata-Version: 2.1
Name: django-dragndrop-related
Version: 0.3.0
Summary: Drag-and-drop multiple uploading of related images/files for
Home-page: http://github.com/BigglesZX/django-dragndrop-related
Author: James Tiplady
Maintainer: James Tiplady
License: MIT
Keywords: django
Platform: OS Independent
Classifier: Development Status :: 4 - Beta
Classifier: Environment :: Web Environment
Classifier: Intended Audience :: Developers
Classifier: License :: OSI Approved :: MIT License
Classifier: Operating System :: OS Independent
Classifier: Programming Language :: Python
Classifier: Programming Language :: Python :: 3.6
Classifier: Topic :: Software Development :: Libraries :: Python Modules
Classifier: Topic :: Software Development :: Libraries :: Application Frameworks
Classifier: Framework :: Django
Classifier: Framework :: Django :: 3.2
Classifier: Framework :: Django :: 4.0
Requires-Python: >=3.6,<4
Provides-Extra: dev
License-File: LICENSE
